dbnd_test_scenarios/__init__.py
dbnd_test_scenarios/scenarios_repo.py
dbnd_test_scenarios/airflow_scenarios/__init__.py
dbnd_test_scenarios/airflow_scenarios/airflow_int_test_utils.py
dbnd_test_scenarios/airflow_scenarios/client_scoring/__init__.py
dbnd_test_scenarios/airflow_scenarios/client_scoring/ingest_data.py
dbnd_test_scenarios/data_health/data_health.py
dbnd_test_scenarios/pipelines/__init__.py
dbnd_test_scenarios/pipelines/bad_pipeline.py
dbnd_test_scenarios/pipelines/large_pipeline.py
dbnd_test_scenarios/pipelines/large_subpipelines.py
dbnd_test_scenarios/pipelines/pipe_4tasks.py
dbnd_test_scenarios/pipelines/preview_pipeline_values.py
dbnd_test_scenarios/pipelines/retry_scenario.py
dbnd_test_scenarios/pipelines/scheduler_scenarios.py
dbnd_test_scenarios/pipelines/simple_pipeline.py
dbnd_test_scenarios/pipelines/simple_read_write_pipeline.py
dbnd_test_scenarios/pipelines/task_examples.py
dbnd_test_scenarios/pipelines/tasks_within_tasks.py
dbnd_test_scenarios/pipelines/ui_functionality.py
dbnd_test_scenarios/pipelines/client_scoring/__init__.py
dbnd_test_scenarios/pipelines/client_scoring/ingest_data.py
dbnd_test_scenarios/pipelines/client_scoring/train.py
dbnd_test_scenarios/pipelines/common/__init__.py
dbnd_test_scenarios/pipelines/common/pandas_tasks.py
dbnd_test_scenarios/pipelines/errors/__init__.py
dbnd_test_scenarios/pipelines/errors/canceled_run_pipeline.py
dbnd_test_scenarios/pipelines/errors/error_deco_extra_param.py
dbnd_test_scenarios/pipelines/errors/error_deco_unknown_type.py
dbnd_test_scenarios/pipelines/errors/error_double_fault.py
dbnd_test_scenarios/pipelines/errors/error_fetch_data.py
dbnd_test_scenarios/pipelines/errors/error_pipelines.py
dbnd_test_scenarios/pipelines/errors/error_read_custom_dict_types.py
dbnd_test_scenarios/pipelines/errors/error_write_read_db_pipeline.py
dbnd_test_scenarios/pipelines/errors/handle_error.py
dbnd_test_scenarios/pipelines/errors/heartbeat_error_handling.py
dbnd_test_scenarios/spark/__init__.py
dbnd_test_scenarios-1.0.30.1.dist-info/LICENSE
dbnd_test_scenarios-1.0.30.1.dist-info/METADATA
dbnd_test_scenarios-1.0.30.1.dist-info/WHEEL
dbnd_test_scenarios-1.0.30.1.dist-info/top_level.txt
dbnd_test_scenarios-1.0.30.1.dist-info/RECORD
